verifier_sujet/__init__.py
verifier_sujet/__main__.py
qa_e_nsi-1.0.0b2.dist-info/METADATA
qa_e_nsi-1.0.0b2.dist-info/WHEEL
qa_e_nsi-1.0.0b2.dist-info/entry_points.txt
qa_e_nsi-1.0.0b2.dist-info/top_level.txt
qa_e_nsi-1.0.0b2.dist-info/RECORD
